MemoryDiagnosticTool/MDT_BDAT_Summary.py
MemoryDiagnosticTool/MDT_eye_template.py
MemoryDiagnosticTool/MDT_html_template.py
MemoryDiagnosticTool/MR_readout_v1.py
MemoryDiagnosticTool/MemoryDiagnosticTool.py
MemoryDiagnosticTool/Trained_CSR_CSV.py
MemoryDiagnosticTool/Trained_LOG_CSV.py
MemoryDiagnosticTool/__init__.py
MemoryDiagnosticTool/chseq.py
MemoryDiagnosticTool/dca_dcs_eye.py
MemoryDiagnosticTool/esid_complete_parser.py
MemoryDiagnosticTool/memtest_parser.py
MemoryDiagnosticTool/postcode.py
MemoryDiagnosticTool/rd_eye_scan.py
MemoryDiagnosticTool/rd_wr_eye.py
MemoryDiagnosticTool/rrw_error_count_parser.py
MemoryDiagnosticTool/trained_phycsr_subset.py
memorydiagnostictool-0.18.0.dist-info/METADATA
memorydiagnostictool-0.18.0.dist-info/WHEEL
memorydiagnostictool-0.18.0.dist-info/top_level.txt
memorydiagnostictool-0.18.0.dist-info/RECORD
