Metadata-Version: 2.1
Name: memorydiagnostictool
Version: 0.18.0
Summary: Memory Diagnostic Tool
Home-page: https://confluence.amd.com/pages/viewpage.action?pageId=1673447643
Author: Tan Sau Kae
License: MIT
Classifier: Programming Language :: Python :: 3
Classifier: License :: OSI Approved :: MIT License
Classifier: Operating System :: OS Independent
Requires-Python: >=3.10
